design.sv

module BCD(clk, rst_asyn, Q_out);
 input clk;
 input rst_asyn;
 output [3:0] Q_out;
 reg [3:0] Q_out;
initial begin            //設定Q_out初始值
 Q_out=0'b0000;
end
always@ (posedge clk or posedge rst_asyn)    //每當clock上升或reset上升
 begin
 if (rst_asyn)          //當reset上升
  Q_out=0'b0000;
 else if (Q_out==15)    //當Q_out已經等於15
  Q_out=0'b0000;
 else
  Q_out++;
 end
endmodule

testbench.sv

module BCD_tb;
  reg clk_tb;
  reg rst_asyn_tb;
  BCD BCD_1(.clk(clk_tb),.rst_asyn(rst_asyn_tb));
initial begin                //設定clock和reset的初始值
  clk_tb=0'b0;
  rst_asyn_tb=0'b0;
end
always begin                //clock的變動頻率
  #10 clk_tb=~clk_tb;
end
initial begin               //設定reset變化時間
  #80 rst_asyn_tb=0'b0;
  #10 rst_asyn_tb=1'b1;
  #10 rst_asyn_tb=0'b0;
  #320 $finish;             
end
initial begin               //輸出結果
  $dumpfile("BCD.vcd");
  $dumpvars(0,BCD_1);
end
endmodule

BCD.vcd
$date
	Sun May  1 18:10:36 2022
$end
$version
	Icarus Verilog
$end
$timescale
	1s
$end
$scope module BCD_tb $end
$scope module BCD_1 $end
$var wire 1 ! clk $end
$var wire 1 " rst_asyn $end
$var reg 4 # Q_out [3:0] $end
$upscope $end
$upscope $end
$enddefinitions $end
#0
$dumpvars
b0 #
0"
0!
$end
#10
b1 #
1!
#20
0!
#30
b10 #
1!
#40
0!
#50
b11 #
1!
#60
0!
#70
b100 #
1!
#80
0!
#90
b0 #
1!
1"
#100
0!
0"
#110
b1 #
1!
#120
0!
#130
b10 #
1!
#140
0!
#150
b11 #
1!
#160
0!
#170
b100 #
1!
#180
0!
#190
b101 #
1!
#200
0!
#210
b110 #
1!
#220
0!
#230
b111 #
1!
#240
0!
#250
b1000 #
1!
#260
0!
#270
b1001 #
1!
#280
0!
#290
b1010 #
1!
#300
0!
#310
b1011 #
1!
#320
0!
#330
b1100 #
1!
#340
0!
#350
b1101 #
1!
#360
0!
#370
b1110 #
1!
#380
0!
#390
b1111 #
1!
#400
0!
#410
b0 #
1!
